firmware_content_extractor/__init__.py
firmware_content_extractor/cli.py
firmware_content_extractor/direct.py
firmware_content_extractor/fasturl.py
firmware_content_extractor/network.py
firmware_content_extractor/parser.py
firmware_content_extractor/payload.py
firmware_content_extractor-1.0.0.dist-info/METADATA
firmware_content_extractor-1.0.0.dist-info/WHEEL
firmware_content_extractor-1.0.0.dist-info/entry_points.txt
firmware_content_extractor-1.0.0.dist-info/top_level.txt
firmware_content_extractor-1.0.0.dist-info/RECORD
