Metadata-Version: 2.4
Name: firmware-content-extractor
Version: 1.0.0
Summary: Extract specific files from remote ROM.ZIP archives without downloading the complete ROM
Author: offici5l
Project-URL: Repository, https://github.com/offici5l/fce
Requires-Python: >=3.8
Requires-Dist: aiohttp
Requires-Dist: zstandard
